boost_utils/__init__.py
boost_utils/bstu.py
boost_utils/clean_utility.py
boost_utils/file_utility.py
boost_utils/misc_utility.py
boost_utils-0.1.dist-info/DESCRIPTION.rst
boost_utils-0.1.dist-info/METADATA
boost_utils-0.1.dist-info/RECORD
boost_utils-0.1.dist-info/WHEEL
boost_utils-0.1.dist-info/metadata.json
boost_utils-0.1.dist-info/top_level.txt
