Metadata-Version: 2.0
Name: boost-utils
Version: 0.1
Summary: Boost Real Estate AI utility package
Home-page: http://boost.nextace.com
Author: Erguder, Freire, Hansen, Zhang
Author-email: dreez@nextace.com
License: MIT
Keywords: Boost NextAce Fidelity National Real Estate
Platform: UNKNOWN
Classifier: Development Status :: 3 - Alpha
Classifier: Intended Audience :: Developers
Classifier: License :: OSI Approved :: MIT License
Classifier: Programming Language :: Python :: 3.5
Classifier: Topic :: Scientific/Engineering :: Artificial Intelligence
Classifier: Topic :: Software Development :: Libraries :: Python Modules
Classifier: Topic :: Text Processing :: Linguistic
Classifier: Topic :: Utilities
